MANIFEST.in
README.rst
buildout.cfg
requirements.txt
setup.py
version.txt
bob/__init__.py
bob.db.batl.egg-info/PKG-INFO
bob.db.batl.egg-info/SOURCES.txt
bob.db.batl.egg-info/dependency_links.txt
bob.db.batl.egg-info/entry_points.txt
bob.db.batl.egg-info/not-zip-safe
bob.db.batl.egg-info/requires.txt
bob.db.batl.egg-info/top_level.txt
bob/db/__init__.py
bob/db/batl/__init__.py
bob/db/batl/batl_config.py
bob/db/batl/create.py
bob/db/batl/db.sql3
bob/db/batl/driver.py
bob/db/batl/files.txt
bob/db/batl/generate_metadata.py
bob/db/batl/loader.py
bob/db/batl/metadata.json
bob/db/batl/models.py
bob/db/batl/query.py
bob/db/batl/test.py
bob/db/batl/config/20_to_23_april_config.json
bob/db/batl/config/24_april_to_july.json
bob/db/batl/config/data_config.json
bob/db/batl/config/default_data_config.json
bob/db/batl/config/rgb_nir_d_annotations.json
doc/conf.py
doc/index.rst