Metadata-Version: 1.1
Name: bob.db.batl
Version: 1.0.0
Summary: Implements a low-level database interface for the BATL database, which is designed for spoofing or presentation attack detection experiments in face biometrics.
Home-page: https://gitlab.idiap.ch/bob/bob.db.batl
Author: Salim Kayal
Author-email: salim.kayal@idiap.ch
License: GPLv3
Keywords: bob
Platform: UNKNOWN
Classifier: Framework :: Bob
Classifier: Development Status :: 3 - Alpha
Classifier: Intended Audience :: Developers
Classifier: License :: OSI Approved :: GNU General Public License v3 (GPLv3)
Classifier: Natural Language :: English
Classifier: Programming Language :: Python
Classifier: Topic :: Scientific/Engineering :: Artificial Intelligence
